MofanJiqiXuexiXilieJiaocheng20201031/README.md
MofanJiqiXuexiXilieJiaocheng20201031/__init__.py
MofanJiqiXuexiXilieJiaocheng20201031/__main__.py
MofanJiqiXuexiXilieJiaocheng20201031/file.epub
MofanJiqiXuexiXilieJiaocheng20201031/index.html
MofanJiqiXuexiXilieJiaocheng20201031/css/__init__.py
MofanJiqiXuexiXilieJiaocheng20201031/css/annotations.css
MofanJiqiXuexiXilieJiaocheng20201031/css/main.css
MofanJiqiXuexiXilieJiaocheng20201031/css/normalize.css
MofanJiqiXuexiXilieJiaocheng20201031/css/popup.css
MofanJiqiXuexiXilieJiaocheng20201031/font/__init__.py
MofanJiqiXuexiXilieJiaocheng20201031/font/fontello.eot
MofanJiqiXuexiXilieJiaocheng20201031/font/fontello.svg
MofanJiqiXuexiXilieJiaocheng20201031/font/fontello.ttf
MofanJiqiXuexiXilieJiaocheng20201031/font/fontello.woff
MofanJiqiXuexiXilieJiaocheng20201031/img/__init__.py
MofanJiqiXuexiXilieJiaocheng20201031/img/annotator-glyph-sprite.png
MofanJiqiXuexiXilieJiaocheng20201031/img/annotator-icon-sprite.png
MofanJiqiXuexiXilieJiaocheng20201031/img/apple-touch-icon.png
MofanJiqiXuexiXilieJiaocheng20201031/img/cancelfullscreen.png
MofanJiqiXuexiXilieJiaocheng20201031/img/close.png
MofanJiqiXuexiXilieJiaocheng20201031/img/fullscreen.png
MofanJiqiXuexiXilieJiaocheng20201031/img/loader.gif
MofanJiqiXuexiXilieJiaocheng20201031/img/menu-icon.png
MofanJiqiXuexiXilieJiaocheng20201031/img/save.png
MofanJiqiXuexiXilieJiaocheng20201031/img/saved.png
MofanJiqiXuexiXilieJiaocheng20201031/img/settings-s.png
MofanJiqiXuexiXilieJiaocheng20201031/img/settings.png
MofanJiqiXuexiXilieJiaocheng20201031/img/star.png
MofanJiqiXuexiXilieJiaocheng20201031/js/__init__.py
MofanJiqiXuexiXilieJiaocheng20201031/js/epub.js
MofanJiqiXuexiXilieJiaocheng20201031/js/epub.min.js
MofanJiqiXuexiXilieJiaocheng20201031/js/epub.min.map
MofanJiqiXuexiXilieJiaocheng20201031/js/hooks.min.js
MofanJiqiXuexiXilieJiaocheng20201031/js/hooks.min.map
MofanJiqiXuexiXilieJiaocheng20201031/js/reader.js
MofanJiqiXuexiXilieJiaocheng20201031/js/reader.js.map
mofan_jiqi_xuexi_xilie_jiaocheng_2020_10_31-2024.3.5.0.dist-info/METADATA
mofan_jiqi_xuexi_xilie_jiaocheng_2020_10_31-2024.3.5.0.dist-info/WHEEL
mofan_jiqi_xuexi_xilie_jiaocheng_2020_10_31-2024.3.5.0.dist-info/entry_points.txt
mofan_jiqi_xuexi_xilie_jiaocheng_2020_10_31-2024.3.5.0.dist-info/top_level.txt
mofan_jiqi_xuexi_xilie_jiaocheng_2020_10_31-2024.3.5.0.dist-info/RECORD
